my_solutions/15.round_robin/rtl/round_robin.v


`timescale 1ns/1ps


module round_robin #(parameter WID=16) (
     input clk, input rst_n
    ,input [WID-1:0] requests
    ,output [WID-1:0] grants
);

localparam WADDR = $clog2(WID);
reg [WADDR-1:0] ptr;


wire have_requests = requests!=0;

reg [1:0] state;

always @(posedge clk or negedge rst_n) begin
    if (!rst_n) begin
        ptr <= 0;
        state <= 0;
    end else begin
        if (state==0) begin
            if (have_requests) begin
                state <= 1;
            end
        end else if (state == 1) begin
            if (requests[ptr]) begin
               state <= 2; 
            end else begin
                ptr <= (ptr==(WID-1)) ? 0 : (ptr + 1);
            end
        end else if (state == 2) begin
            state <= 0;
            ptr <= (ptr==(WID-1)) ? 0 : (ptr + 1);
        end
    end
end

assign grants = (state==2) ? (1<<ptr) : 0;


endmodule

my_solutions/15.round_robin/rtl/tb.v
`timescale 1ns/1ps
module tb;
integer    cycles;   initial cycles=0;
integer    errors;   initial errors=0;
integer    wrongs;   initial wrongs=0;
integer    panics;   initial panics=0;
integer    corrects; initial corrects=0;
integer    seqptr; initial seqptr=0;
reg [255:0] markstr;   initial markstr=0;
reg [31:0] mark;   initial mark=0;
reg [31:0] marker;   initial marker=0;
reg [31:0] marker0;   initial marker0=0;
reg [31:0] marker1;   initial marker1=0;
reg [31:0] marker2;   initial marker2=0;
reg [31:0] marker3;   initial marker3=0;
reg [31:0] Index;   initial Index=0;
reg [31:0] ID;   initial ID=0;
parameter WID = 16;
reg  clk;
wire [(WID - 1):0] grants;
reg [(WID - 1):0] requests;
reg  rst_n;

always begin
    clk=0;
    #10;
    clk=1;
    #3;
    $python("negedge()");
    #7;
end
initial begin
    $dumpvars(0,tb);
    rst_n = 0;
    clk = 0;
    requests = 0;
    rst_n = 0;
    #100;
    rst_n=1;
end
round_robin dut (
     .clk(clk)
    ,.grants(grants[(WID - 1):0])
    ,.requests(requests[(WID - 1):0])
    ,.rst_n(rst_n)
);

reg [1023:0] testname;
initial begin
    if ($value$plusargs("LOG=%s",testname)) begin 
        $python("pymonname()",testname);
    end 


    if ($value$plusargs("SEQ=%s",testname)) begin 
         $display(" Running SEQ= %s.",testname); 
    end else begin
        testname = 0;
        $display(" default test");
    end 
    #10;
    if (testname!=0) $python("sequence()",testname);
end 
endmodule


module inout_driver ( inout io , input dflt );

reg val; initial val=0;
reg drive; initial drive=0;
assign io = drive ? val : 1'bz;
assign (pull1,pull0) io = dflt;

endmodule

my_solutions/15.round_robin/dump.vcd
$date
	Thu Aug 15 15:34:34 2024
$end
$version
	Icarus Verilog
$end
$timescale
	1ps
$end
$scope module tb $end
$var wire 16 ! grants [15:0] $end
$var parameter 32 " WID $end
$var reg 32 # ID [31:0] $end
$var reg 32 $ Index [31:0] $end
$var reg 1 % clk $end
$var reg 32 & mark [31:0] $end
$var reg 32 ' marker [31:0] $end
$var reg 32 ( marker0 [31:0] $end
$var reg 32 ) marker1 [31:0] $end
$var reg 32 * marker2 [31:0] $end
$var reg 32 + marker3 [31:0] $end
$var reg 256 , markstr [255:0] $end
$var reg 16 - requests [15:0] $end
$var reg 1 . rst_n $end
$var reg 1024 / testname [1023:0] $end
$var integer 32 0 corrects [31:0] $end
$var integer 32 1 cycles [31:0] $end
$var integer 32 2 errors [31:0] $end
$var integer 32 3 panics [31:0] $end
$var integer 32 4 seqptr [31:0] $end
$var integer 32 5 wrongs [31:0] $end
$scope module dut $end
$var wire 1 % clk $end
$var wire 16 6 requests [15:0] $end
$var wire 1 . rst_n $end
$var wire 1 7 have_requests $end
$var wire 16 8 grants [15:0] $end
$var parameter 32 9 WADDR $end
$var parameter 32 : WID $end
$var reg 4 ; ptr [3:0] $end
$var reg 2 < state [1:0] $end
$upscope $end
$upscope $end
$enddefinitions $end
$comment Show the parameter values. $end
$dumpall
b10000 :
b100 9
b10000 "
$end
#0
$dumpvars
b0 <
b0 ;
b0 8
07
b0 6
b0 5
b0 4
b0 3
b0 2
b0 1
b0 0
b111010001100101011100110111010000101110011100110110010101110001 /
0.
b0 -
b0 ,
b0 +
b0 *
b0 )
b0 (
b0 '
b0 &
0%
b0 $
b0 #
b0 !
$end
#10000
1%
#13000
b1 1
#20000
0%
#30000
1%
#33000
b10 1
#40000
0%
#50000
1%
#53000
b11 1
#60000
0%
#70000
1%
#73000
b100 1
#80000
0%
#90000
1%
#93000
b101 1
#100000
0%
1.
#110000
1%
#113000
b110 1
#120000
0%
#130000
1%
#133000
b111 1
#140000
0%
#150000
1%
#153000
b1000 1
#160000
0%
#170000
1%
#173000
b1001 1
#180000
0%
#190000
1%
#193000
b1010 1
#200000
0%
#210000
1%
#213000
b1011 1
#220000
0%
#230000
1%
#233000
b1100 1
#240000
0%
#250000
1%
#253000
b1101 1
#260000
0%
#270000
1%
#273000
b1110 1
#280000
0%
#290000
1%
#293000
b1111 1
#300000
0%
#310000
1%
#313000
b10000 1
#320000
0%
#330000
1%
#333000
b10001 1
#340000
0%
#350000
1%
#353000
b10010 1
#360000
0%
#370000
1%
#373000
b10011 1
#380000
0%
#390000
1%
#393000
b10100 1
#400000
0%
#410000
1%
#413000
b10101 1
#420000
0%
#430000
1%
#433000
b10110 1
#440000
0%
#450000
1%
#453000
b10111 1
#460000
0%
#470000
1%
#473000
b11000 1
#480000
0%
#490000
1%
#493000
b11001 1
#500000
0%
#510000
1%
#513000
b11010 1
#520000
0%
#530000
1%
#533000
b11011 1
#540000
0%
#550000
1%
#553000
b11100 1
#560000
0%
#570000
1%
#573000
b11101 1
#580000
0%
#590000
1%
#593000
b11110 1
#600000
0%
#610000
1%
#613000
b11 4
b11111 1
#620000
0%
#630000
1%
#633000
b100000 1
#640000
0%
#650000
1%
#653000
b100001 1
#660000
0%
#670000
1%
#673000
b100010 1
#680000
0%
#690000
1%
#693000
17
b1 -
b1 6
b100 4
b100011 1
#700000
0%
#710000
b1 <
1%
#713000
b101 4
b100100 1
#720000
0%
#730000
b1 !
b1 8
b10 <
1%
#733000
b100101 1
#740000
0%
#750000
b0 !
b0 8
b1 ;
b0 <
1%
#753000
b10 -
b10 6
b110 4
b100110 1
#760000
0%
#770000
b1 <
1%
#773000
b111 4
b100111 1
#780000
0%
#790000
b10 !
b10 8
b10 <
1%
#793000
b101000 1
#800000
0%
#810000
b0 !
b0 8
b10 ;
b0 <
1%
#813000
b100 -
b100 6
b1000 4
b101001 1
#820000
0%
#830000
b1 <
1%
#833000
b1001 4
b101010 1
#840000
0%
#850000
b100 !
b100 8
b10 <
1%
#853000
b101011 1
#860000
0%
#870000
b0 !
b0 8
b11 ;
b0 <
1%
#873000
b1111 -
b1111 6
b1010 4
b101100 1
#880000
0%
#890000
b1 <
1%
#893000
b1011 4
b101101 1
#900000
0%
#910000
b1000 !
b1000 8
b10 <
1%
#913000
b101110 1
#920000
0%
#930000
b0 !
b0 8
b100 ;
b0 <
1%
#933000
b101111 1
#940000
0%
#950000
b1 <
1%
#953000
b110000 1
#960000
0%
#970000
b101 ;
1%
#973000
b110001 1
#980000
0%
#990000
b110 ;
1%
#993000
b110010 1
#1000000
0%
#1010000
b111 ;
1%
#1013000
b110011 1
#1020000
0%
#1030000
b1000 ;
1%
#1033000
b110100 1
#1040000
0%
#1050000
b1001 ;
1%
#1053000
b110101 1
#1060000
0%
#1070000
b1010 ;
1%
#1073000
b110110 1
#1080000
0%
#1090000
b1011 ;
1%
#1093000
b110111 1
#1100000
0%
#1110000
b1100 ;
1%
#1113000
b111000 1
#1120000
0%
#1130000
b1101 ;
1%
#1133000
b111001 1
#1140000
0%
#1150000
b1110 ;
1%
#1153000
b111010 1
#1160000
0%
#1170000
b1111 ;
1%
#1173000
b111011 1
#1180000
0%
#1190000
b0 ;
1%
#1193000
b111100 1
#1200000
0%
#1210000
b1 !
b1 8
b10 <
1%
#1213000
b111101 1
#1220000
0%
#1230000
b0 !
b0 8
b1 ;
b0 <
1%
#1233000
b111110 1
#1240000
0%
#1250000
b1 <
1%
#1253000
b111111 1
#1260000
0%
#1270000
b10 !
b10 8
b10 <
1%
#1273000
b1000000 1
#1280000
0%
#1290000
b0 !
b0 8
b10 ;
b0 <
1%
#1293000
b1000001 1
#1300000
0%
#1310000
b1 <
1%
#1313000
b1000010 1
#1320000
0%
#1330000
b100 !
b100 8
b10 <
1%
#1333000
b1000011 1
#1340000
0%
#1350000
b0 !
b0 8
b11 ;
b0 <
1%
#1353000
b1100 4
b1000100 1
#1360000
0%
#1370000
b1 <
1%
#1373000
b1000101 1
#1380000
0%
#1390000
b1000 !
b1000 8
b10 <
1%
#1393000
b1000110 1
#1400000
0%
#1410000
b0 !
b0 8
b100 ;
b0 <
1%
#1413000
b1000111 1
#1420000
0%
#1430000
b1 <
1%
#1433000
b1001000 1
#1440000
0%
#1450000
b101 ;
1%
#1453000
b1001001 1
#1460000
0%
#1470000
b110 ;
1%
#1473000
b1001010 1
#1480000
0%
#1490000
b111 ;
1%
#1493000
b1001011 1
#1500000
0%
#1510000
b1000 ;
1%
#1513000
b1001100 1
#1520000
0%
#1530000
b1001 ;
1%
#1533000
b1001101 1
#1540000
0%
#1550000
b1010 ;
1%
#1553000
b1001110 1
#1560000
0%
#1570000
b1011 ;
1%
#1573000
b1001111 1
#1580000
0%
#1590000
b1100 ;
1%
#1593000
b1010000 1
#1600000
0%
#1610000
b1101 ;
1%
#1613000
b1010001 1
#1620000
0%
#1630000
b1110 ;
1%
#1633000
b1010010 1
#1640000
0%
#1650000
b1111 ;
1%
#1653000
b1010011 1
#1660000
0%
#1670000
b0 ;
1%
