vcdTester/rtl/synchronizer_level.v

`timescale 1ns / 1ps

module synchronizer_level #(parameter WID=1) (
    input clk, input [WID-1:0] din, input rst_n,output [WID-1:0] dout
);

reg [WID-1:0] SYNCFLOP0,SYNCFLOP1;
always @(posedge clk or negedge rst_n) begin
    if (!rst_n) begin
        SYNCFLOP0 <= 1'b0;
        SYNCFLOP1 <= 1'b0;
    end else begin
        SYNCFLOP0 <= din;
        SYNCFLOP1 <= SYNCFLOP0;
    end
end
assign dout = SYNCFLOP1;


wire [63:0]  sign_version = 64'h00006ebd11060323 ;
endmodule

vcdTester/rtl/async_stage.v
`timescale 1ns / 1ps
module async_stage #(parameter WID=32)(
     input wclk
    ,input rst_nw
    ,input rclk
    ,input rst_nr
    ,input writex
    ,output wfull
    ,input [WID-1:0] wdata
    ,output reg  [WID-1:0] LVL_rdata
    ,output rempty
    ,input  readx
);
reg wtoken,rtoken;
wire wtoken_sync,rtoken_sync;
synchronizer_level syncr (.clk(rclk),.rst_n(rst_nr),.din(wtoken),.dout(wtoken_sync));
synchronizer_level syncw (.clk(wclk),.rst_n(rst_nw),.din(rtoken),.dout(rtoken_sync));
assign wfull  =  wtoken!=rtoken_sync;
assign rempty  =  wtoken_sync==rtoken;
always_ff @(posedge wclk or negedge rst_nw) begin
    if (!rst_nw) begin
        wtoken<=1'b0;
        LVL_rdata <= 1'b0;
    end else begin
        if (!wfull && writex) begin
            LVL_rdata <= wdata;
            wtoken <= !wtoken;
        end
    end
end
always_ff @(posedge rclk or negedge rst_nr) begin
    if (!rst_nr) begin
        rtoken<=1'b0;
    end else begin
        if (!rempty && readx) begin
            rtoken<=~rtoken;
        end
    end
end
wire [63:0]  sign_version = 64'h000127c111060323 ;
endmodule

vcdTester/rtl/async2fifo.v

`timescale 1ns / 1ps
module async2fifo #(parameter WID=32)(
     input wclk
    ,input rst_nw
    ,input rclk
    ,input rst_nr
    ,input writex
    ,output wfull
    ,input [WID-1:0] wdata
    ,output [WID-1:0] rdata
    ,output rempty
    ,input  readx
);

wire [WID-1:0] rdata0;
wire wfull0,rempty0;
wire [WID-1:0] rdata1;
wire wfull1,rempty1;


reg wptr;
always_ff @(posedge wclk or negedge rst_nw) begin
    if (!rst_nw) begin
        wptr<=0;
    end else if (writex && !wfull) begin
        wptr<=wptr+1'b1;
    end
end

assign wfull = ((wptr==0)&&wfull0) ||((wptr==1)&&wfull1) ;
wire writex0 = writex && (wptr==0)&&!wfull0;
wire writex1 = writex && (wptr==1)&&!wfull1;

reg rptr;
always_ff @(posedge rclk or negedge rst_nr) begin
    if (!rst_nr) begin
        rptr<=0;
    end else if (readx && !rempty) begin
        rptr<=rptr+1'd1;
    end
end

assign rdata =
    (rptr== 0) ? rdata0 :
    (rptr== 1) ? rdata1 :
     2'd0;

assign rempty =
    (rptr== 0) ? rempty0 :
    (rptr== 1) ? rempty1 :
     2'd0;

wire readx0 = readx && (rptr== 0);
wire readx1 = readx && (rptr== 1);


async_stage #(WID) stage0 (
     .rclk(rclk) ,.rst_nr(rst_nr)
    ,.wclk(wclk) ,.rst_nw(rst_nw)
    ,.LVL_rdata(rdata0) ,.readx(readx0) ,.rempty(rempty0)
    ,.wdata(wdata) ,.wfull(wfull0) ,.writex(writex0)
);
async_stage #(WID) stage1 (
     .rclk(rclk) ,.rst_nr(rst_nr)
    ,.wclk(wclk) ,.rst_nw(rst_nw)
    ,.LVL_rdata(rdata1) ,.readx(readx1) ,.rempty(rempty1)
    ,.wdata(wdata) ,.wfull(wfull1) ,.writex(writex1)
);


wire [63:0]  sign_version = 64'h0001a5af23220623 ;
endmodule

vcdTester/rtl/tb.v
`timescale 1ns/1ps
module tb;
integer    cycles;   initial cycles=0;
integer    errors;   initial errors=0;
integer    wrongs;   initial wrongs=0;
integer    panics;   initial panics=0;
integer    corrects; initial corrects=0;
integer    seqptr; initial seqptr=0;
reg [255:0] markstr;   initial markstr=0;
reg [31:0] mark;   initial mark=0;
reg [31:0] marker;   initial marker=0;
reg [31:0] marker0;   initial marker0=0;
reg [31:0] marker1;   initial marker1=0;
reg [31:0] marker2;   initial marker2=0;
reg [31:0] marker3;   initial marker3=0;
reg [31:0] Index;   initial Index=0;
reg [31:0] ID;   initial ID=0;
parameter WID = 32;
reg  rclk;
wire [(WID - 1):0] rdata;
reg  readx;
wire  rempty;
reg  rst_nr;
reg  rst_nw;
reg  wclk;
reg [(WID - 1):0] wdata;
wire  wfull;
reg  writex;
wire rst_n = rst_nw;
wire clk = wclk;

always begin
    wclk=0;
    #10;
    wclk=1;
    #2;
    $python("wnegedge()");
    #1;
end

always begin
    rclk=0;
    #10;
    rclk=1;
    #3;
    $python("rnegedge()");
    #4;
end

initial begin
    $dumpvars(0,tb);
    rclk = 0;
    readx = 0;
    rst_nr = 0;
    rst_nw = 0;
    wclk = 0;
    wdata = 0;
    writex = 0;
    #100;
    rst_nr = 1;
    rst_nw = 1;
end
async2fifo dut (
     .rclk(rclk)
    ,.rdata(rdata[(WID - 1):0])
    ,.readx(readx)
    ,.rempty(rempty)
    ,.rst_nr(rst_nr)
    ,.rst_nw(rst_nw)
    ,.wclk(wclk)
    ,.wdata(wdata[(WID - 1):0])
    ,.wfull(wfull)
    ,.writex(writex)
);

reg [1023:0] testname;
initial begin
    if ($value$plusargs("LOG=%s",testname)) begin 
        $python("pymonname()",testname);
    end 


    if ($value$plusargs("SEQ=%s",testname)) begin 
         $display(" Running SEQ= %s.",testname); 
    end else begin
        testname = 0;
        $display(" default test");
    end 
    #10;
    if (testname!=0) $python("sequence()",testname);
end 
endmodule


module inout_driver ( inout io , input dflt );

reg val; initial val=0;
reg drive; initial drive=0;
assign io = drive ? val : 1'bz;
assign (pull1,pull0) io = dflt;

endmodule

vcdTester/soc_tb/dump.vcd
$date
	Wed May 15 10:52:44 2024
$end
$version
	Icarus Verilog
$end
$timescale
	1ps
$end
$scope module tb $end
$var wire 1 ! clk $end
$var wire 1 " rst_n $end
$var wire 1 # wfull $end
$var wire 1 $ rempty $end
$var wire 32 % rdata [31:0] $end
$var parameter 32 & WID $end
$var reg 32 ' ID [31:0] $end
$var reg 32 ( Index [31:0] $end
$var reg 32 ) mark [31:0] $end
$var reg 32 * marker [31:0] $end
$var reg 32 + marker0 [31:0] $end
$var reg 32 , marker1 [31:0] $end
$var reg 32 - marker2 [31:0] $end
$var reg 32 . marker3 [31:0] $end
$var reg 256 / markstr [255:0] $end
$var reg 1 0 rclk $end
$var reg 1 1 readx $end
$var reg 1 2 rst_nr $end
$var reg 1 3 rst_nw $end
$var reg 1024 4 testname [1023:0] $end
$var reg 1 5 wclk $end
$var reg 32 6 wdata [31:0] $end
$var reg 1 7 writex $end
$var integer 32 8 corrects [31:0] $end
$var integer 32 9 cycles [31:0] $end
$var integer 32 : errors [31:0] $end
$var integer 32 ; panics [31:0] $end
$var integer 32 < seqptr [31:0] $end
$var integer 32 = wrongs [31:0] $end
$scope module dut $end
$var wire 1 0 rclk $end
$var wire 1 1 readx $end
$var wire 1 > readx0 $end
$var wire 1 ? readx1 $end
$var wire 1 2 rst_nr $end
$var wire 1 3 rst_nw $end
$var wire 64 @ sign_version [63:0] $end
$var wire 1 5 wclk $end
$var wire 32 A wdata [31:0] $end
$var wire 1 # wfull $end
$var wire 1 7 writex $end
$var wire 1 B writex0 $end
$var wire 1 C writex1 $end
$var wire 1 D wfull1 $end
$var wire 1 E wfull0 $end
$var wire 1 F rempty1 $end
$var wire 1 G rempty0 $end
$var wire 1 $ rempty $end
$var wire 32 H rdata1 [31:0] $end
$var wire 32 I rdata0 [31:0] $end
$var wire 32 J rdata [31:0] $end
$var parameter 32 K WID $end
$var reg 1 L rptr $end
$var reg 1 M wptr $end
$scope module stage0 $end
$var wire 1 0 rclk $end
$var wire 1 > readx $end
$var wire 1 G rempty $end
$var wire 1 2 rst_nr $end
$var wire 1 3 rst_nw $end
$var wire 64 N sign_version [63:0] $end
$var wire 1 5 wclk $end
$var wire 32 O wdata [31:0] $end
$var wire 1 E wfull $end
$var wire 1 B writex $end
$var wire 1 P wtoken_sync $end
$var wire 1 Q rtoken_sync $end
$var parameter 32 R WID $end
$var reg 32 S LVL_rdata [31:0] $end
$var reg 1 T rtoken $end
$var reg 1 U wtoken $end
$scope module syncr $end
$var wire 1 0 clk $end
$var wire 1 U din $end
$var wire 1 P dout $end
$var wire 1 2 rst_n $end
$var wire 64 V sign_version [63:0] $end
$var parameter 32 W WID $end
$var reg 1 X SYNCFLOP0 $end
$var reg 1 P SYNCFLOP1 $end
$upscope $end
$scope module syncw $end
$var wire 1 5 clk $end
$var wire 1 T din $end
$var wire 1 Q dout $end
$var wire 1 3 rst_n $end
$var wire 64 Y sign_version [63:0] $end
$var parameter 32 Z WID $end
$var reg 1 [ SYNCFLOP0 $end
$var reg 1 Q SYNCFLOP1 $end
$upscope $end
$upscope $end
$scope module stage1 $end
$var wire 1 0 rclk $end
$var wire 1 ? readx $end
$var wire 1 F rempty $end
$var wire 1 2 rst_nr $end
$var wire 1 3 rst_nw $end
$var wire 64 \ sign_version [63:0] $end
$var wire 1 5 wclk $end
$var wire 32 ] wdata [31:0] $end
$var wire 1 D wfull $end
$var wire 1 C writex $end
$var wire 1 ^ wtoken_sync $end
$var wire 1 _ rtoken_sync $end
$var parameter 32 ` WID $end
$var reg 32 a LVL_rdata [31:0] $end
$var reg 1 b rtoken $end
$var reg 1 c wtoken $end
$scope module syncr $end
$var wire 1 0 clk $end
$var wire 1 c din $end
$var wire 1 ^ dout $end
$var wire 1 2 rst_n $end
$var wire 64 d sign_version [63:0] $end
$var parameter 32 e WID $end
$var reg 1 f SYNCFLOP0 $end
$var reg 1 ^ SYNCFLOP1 $end
$upscope $end
$scope module syncw $end
$var wire 1 5 clk $end
$var wire 1 b din $end
$var wire 1 _ dout $end
$var wire 1 3 rst_n $end
$var wire 64 g sign_version [63:0] $end
$var parameter 32 h WID $end
$var reg 1 i SYNCFLOP0 $end
$var reg 1 _ SYNCFLOP1 $end
$upscope $end
$upscope $end
$upscope $end
$upscope $end
$enddefinitions $end
$comment Show the parameter values. $end
$dumpall
b1 h
b1 e
b100000 `
b1 Z
b1 W
b100000 R
b100000 K
b100000 &
$end
#0
$dumpvars
0i
b11011101011110100010001000001100000001100100011 g
0f
b11011101011110100010001000001100000001100100011 d
0c
0b
b0 a
0_
0^
b0 ]
b1001001111100000100010001000001100000001100100011 \
0[
b11011101011110100010001000001100000001100100011 Y
0X
b11011101011110100010001000001100000001100100011 V
0U
0T
b0 S
0Q
0P
b0 O
b1001001111100000100010001000001100000001100100011 N
0M
0L
b0 J
b0 I
b0 H
1G
1F
0E
0D
0C
0B
b0 A
b1101001011010111100100011001000100000011000100011 @
0?
0>
b0 =
b0 <
b0 ;
b0 :
b0 9
b0 8
07
b0 6
05
b0 4
03
02
01
00
b0 /
b0 .
b0 -
b0 ,
b0 +
b0 *
b0 )
b0 (
b0 '
b0 %
1$
0#
0"
0!
$end
#10000
10
1!
15
#12000
b1 9
#13000
0!
05
#17000
00
#23000
1!
15
#25000
b10 9
#26000
0!
05
#27000
10
#34000
00
#36000
1!
15
#38000
b11 9
#39000
0!
05
#44000
10
#49000
1!
15
#51000
b100 9
00
#52000
0!
05
#61000
10
#62000
1!
15
#64000
b101 9
#65000
0!
05
#68000
00
#75000
1!
15
#77000
b110 9
#78000
0!
05
10
#85000
00
#88000
1!
15
#90000
b111 9
#91000
0!
05
#95000
10
#100000
1"
13
12
#101000
1!
15
#102000
00
#103000
b1000 9
#104000
0!
05
#112000
10
#114000
1!
15
#116000
b1001 9
#117000
0!
05
#119000
00
#127000
1!
15
#129000
b1010 9
10
#130000
0!
05
#136000
00
#140000
1!
15
#142000
b1011 9
#143000
0!
05
#146000
10
#153000
00
1!
15
#155000
b1100 9
#156000
0!
05
#163000
10
#166000
1!
15
#168000
b1101 9
#169000
0!
05
#170000
00
#179000
1!
15
#180000
10
#181000
b1110 9
#182000
0!
05
#187000
00
#192000
1!
15
#194000
b1111 9
#195000
0!
05
#197000
10
#204000
00
#205000
1!
15
#207000
b10000 9
#208000
0!
05
#214000
10
#218000
1!
15
#220000
b10001 9
#221000
0!
05
00
#231000
1!
15
10
#233000
b10010 9
#234000
0!
05
#238000
00
#244000
1!
15
#246000
b10011 9
#247000
0!
05
#248000
10
#255000
00
#257000
1!
15
#259000
b10100 9
#260000
0!
05
#265000
10
#270000
1!
15
#272000
b10101 9
00
#273000
0!
05
#282000
10
#283000
1!
15
#285000
b10110 9
#286000
0!
05
#289000
00
#296000
1!
15
#298000
b10111 9
#299000
0!
05
10
#306000
00
#309000
1!
15
#311000
b11000 9
#312000
0!
05
#316000
10
#322000
1!
15
#323000
00
#324000
b11001 9
#325000
0!
05
#333000
10
#335000
1!
15
#337000
b11010 9
#338000
0!
05
#340000
00
#348000
1!
15
#350000
b11011 9
10
#351000
0!
05
#357000
00
#361000
1!
15
#363000
b11100 9
#364000
0!
05
#367000
10
#374000
00
1!
15
#376000
b11101 9
#377000
0!
05
#384000
10
#387000
1!
15
#389000
b11110 9
#390000
0!
05
#391000
00
#400000
1!
15
#401000
10
#402000
b11111 9
#403000
0!
05
#408000
00
#413000
1!
15
#415000
b100000 9
#416000
0!
05
#418000
10
#425000
00
#426000
1!
15
#428000
b100001 9
#429000
0!
05
#435000
10
#439000
1!
15
#441000
1B
b100000100010 6
b100000100010 A
b100000100010 O
b100000100010 ]
17
b100010 9
#442000
0!
05
00
#452000
1C
0B
1E
b100000100010 %
b100000100010 J
1M
1U
b100000100010 I
b100000100010 S
1!
15
10
#454000
0C
b0 6
b0 A
b0 O
b0 ]
07
b100011 9
#455000
0!
05
#459000
00
#465000
1!
15
#467000
1C
b100001000011 6
b100001000011 A
b100001000011 O
b100001000011 ]
17
b100100 9
#468000
0!
05
#469000
1X
10
#476000
00
#478000
1#
0C
1D
0M
1c
b100001000011 H
b100001000011 a
1!
15
#480000
b0 6
b0 A
b0 O
b0 ]
07
b100101 9
#481000
0!
05
#486000
0$
0G
1f
1P
10
#489000
1>
b1 8
11
#491000
1!
15
#493000
b100110 9
00
#494000
0!
05
#503000
0$
1G
0F
b100001000011 %
b100001000011 J
0>
1?
1T
1^
1L
10
#504000
1[
1!
15
#506000
b100111 9
b10 8
#507000
0!
05
#510000
00
#517000
0#
0E
1Q
1!
15
#519000
b101000 9
#520000
1$
b100000100010 %
b100000100010 J
1>
0?
1F
0L
1b
0!
05
10
#523000
0>
01
#527000
00
#530000
1i
1!
15
#532000
1B
b101100101011 6
b101100101011 A
b101100101011 O
b101100101011 ]
17
b101001 9
#533000
0!
05
#537000
10
#543000
0#
0B
1C
1E
b101100101011 %
b101100101011 J
0D
0U
b101100101011 I
b101100101011 S
1_
1M
1!
15
#544000
00
#545000
b110010100100 6
b110010100100 A
b110010100100 O
b110010100100 ]
b101010 9
#546000
0!
05
#554000
0X
10
#556000
1#
0C
1D
0M
0c
b110010100100 H
b110010100100 a
1!
15
#558000
b0 6
b0 A
b0 O
b0 ]
07
b101011 9
#559000
0!
05
#561000
00
#569000
1!
15
#571000
0$
0G
0P
0f
b101100 9
10
#572000
0!
05
#574000
1>
b11 8
11
#578000
00
#582000
1!
15
#584000
b101101 9
#585000
0!
05
#588000
b110010100100 %
b110010100100 J
0>
1?
0F
1G
1L
0^
0T
10
#591000
b100 8
#595000
0[
00
1!
15
#597000
b101110 9
#598000
0!
05
#605000
1$
1F
b101100101011 %
b101100101011 J
1>
0?
0b
0L
10
#608000
0#
0E
0i
0Q
0>
01
1!
15
#610000
1B
b1000100000110 6
b1000100000110 A
b1000100000110 O
b1000100000110 ]
17
b101111 9
#611000
0!
05
#612000
00
#621000
0#
0B
1C
1E
b1000100000110 %
b1000100000110 J
0D
1U
b1000100000110 I
b1000100000110 S
0_
1M
1!
15
#622000
1X
10
#623000
0C
b0 6
b0 A
b0 O
b0 ]
07
b110000 9
#624000
0!
05
#629000
00
#634000
1!
15
#636000
b110001 9
#637000
0!
05
#639000
0$
0G
1P
10
#642000
1>
b101 8
11
#646000
00
#647000
1!
15
#649000
b110010 9
#650000
0!
05
#656000
1$
b110010100100 %
b110010100100 J
0>
1?
1G
1L
1T
10
#659000
0?
01
#660000
1[
1!
15
#662000
1C
b101001010100 6
b101001010100 A
b101001010100 O
b101001010100 ]
17
b110011 9
#663000
0!
05
00
#673000
b101001010100 %
b101001010100 J
0#
1B
0C
0E
1D
1Q
1c
b101001010100 H
b101001010100 a
0M
1!
15
10
#675000
b10010011111 6
b10010011111 A
b10010011111 O
b10010011111 ]
b110100 9
#676000
0!
05
#680000
00
#686000
1#
0B
1E
1M
0U
b10010011111 I
b10010011111 S
1!
15
#688000
b0 6
b0 A
b0 O
b0 ]
07
b110101 9
#689000
0!
05
#690000
1f
0X
10
#697000
00
#699000
1!
15
#701000
b110110 9
#702000
0!
05
#707000
0$
0G
0F
0P
1^
10
#710000
1?
b110 8
11
#712000
1!
15
#714000
b110111 9
00
#715000
0!
05
#724000
b10010011111 %
b10010011111 J
1>
0?
1F
0L
1b
10
#725000
1i
1!
15
#727000
b111000 9
b111 8
#728000
0!
05
#731000
00
#738000
0#
0D
1_
1!
15
#740000
b111001 9
#741000
1$
1G
b101001010100 %
b101001010100 J
0>
1?
0T
1L
0!
05
10
#744000
0?
01
#748000
00
#751000
0[
1!
15
#753000
1C
b1000010001000 6
b1000010001000 A
b1000010001000 O
b1000010001000 ]
17
b111010 9
#754000
0!
05
#758000
10
#764000
0C
b1000010001000 %
b1000010001000 J
1B
1D
0E
0M
0c
b1000010001000 H
b1000010001000 a
0Q
1!
15
#765000
00
#766000
0B
b0 6
b0 A
b0 O
b0 ]
07
b111011 9
#767000
0!
05
#775000
0f
10
#777000
1!
15
#779000
b111100 9
#780000
0!
05
#782000
00
#790000
1!
15
#792000
0$
0F
0^
b111101 9
10
#793000
0!
05
#795000
1?
b1000 8
11
#799000
00
#803000
1!
15
#805000
b111110 9
#806000
0!
05
#809000
1$
1F
b10010011111 %
b10010011111 J
1>
0?
0b
0L
10
#812000
0>
01
#816000
0i
00
1!
15
#818000
b111111 9
#819000
0!
05
#826000
10
#829000
0D
0_
1!
15
#831000
b1000000 9
#832000
0!
05
#833000
00
#842000
1!
15
#843000
10
#844000
b1000001 9
#845000
0!
05
#850000
00
#855000
1!
15
#857000
1B
b110001010101 6
b110001010101 A
b110001010101 O
b110001010101 ]
17
b1000010 9
#858000
0!
05
#860000
10
#867000
00
#868000
1C
0B
1E
b110001010101 %
b110001010101 J
1M
1U
b110001010101 I
b110001010101 S
1!
15
#870000
b1000101111001 6
b1000101111001 A
b1000101111001 O
b1000101111001 ]
b1000011 9
#871000
0!
05
#877000
1X
10
#881000
1#
0C
1D
1c
b1000101111001 H
b1000101111001 a
0M
1!
15
#883000
b0 6
b0 A
b0 O
b0 ]
07
b1000100 9
#884000
0!
05
00
#894000
0$
0G
1f
1P
1!
15
10
#896000
b1000101 9
#897000
1>
0!
05
b1001 8
11
#901000
00
#907000
1!
15
#909000
b1000110 9
#910000
0!
05
#911000
0$
1G
0F
b1000101111001 %
b1000101111001 J
0>
1?
1T
1^
1L
10
#914000
b1010 8
#918000
00
#920000
1[
1!
15
#922000
b1000111 9
#923000
0!
05
#928000
1$
b110001010101 %
b110001010101 J
1>
0?
1F
0L
1b
10
#931000
0>
01
#933000
0#
0E
1Q
1i
1!
15
#935000
b1001000 9
00
#936000
0!
05
#945000
10
#946000
0D
1_
1!
15
#948000
1B
b111001110111 6
b111001110111 A
b111001110111 O
b111001110111 ]
17
b1001001 9
#949000
0!
05
#952000
00
#959000
0B
1C
1E
b111001110111 %
b111001110111 J
0U
b111001110111 I
b111001110111 S
1M
1!
15
#961000
b1001101110000 6
b1001101110000 A
b1001101110000 O
b1001101110000 ]
b1001010 9
#962000
0X
0!
05
10
#969000
00
#972000
1#
0C
1D
0M
0c
b1001101110000 H
b1001101110000 a
1!
15
#974000
b0 6
b0 A
b0 O
b0 ]
07
b1001011 9
#975000
0!
05
#979000
0$
0G
0P
0f
10
#982000
1>
b1011 8
11
#985000
1!
15
#986000
00
#987000
b1001100 9
#988000
0!
05
#996000
b1001101110000 %
b1001101110000 J
0>
1?
0F
1G
1L
0^
0T
10
#998000
0[
1!
15
#999000
b1100 8
#1000000
b1001101 9
#1001000
0!
05
#1003000
00
#1011000
0#
0E
0Q
1!
15
#1013000
1$
1F
b111001110111 %
b111001110111 J
1>
0?
0b
0L
b1001110 9
10
#1014000
0!
05
#1016000
0>
01
#1020000
00
#1024000
0i
1!
15
#1026000
b1001111 9
#1027000
0!
05
#1030000
10
#1037000
0D
0_
00
1!
15
#1039000
1B
b111010111110 6
b111010111110 A
b111010111110 O
b111010111110 ]
17
b1010000 9
#1040000
0!
05
#1047000
10
#1050000
1C
0B
1E
b111010111110 %
b111010111110 J
1M
1U
b111010111110 I
b111010111110 S
1!
15
#1052000
b111000010001 6
b111000010001 A
b111000010001 O
b111000010001 ]
b1010001 9
#1053000
0!
05
#1054000
00
#1063000
1#
0C
1D
1c
b111000010001 H
b111000010001 a
0M
1!
15
#1064000
1f
1X
10
#1065000
b0 6
b0 A
b0 O
b0 ]
07
b1010010 9
#1066000
0!
05
#1071000
00
#1076000
1!
15
#1078000
b1010011 9
#1079000
0!
05
#1081000
0$
0G
0F
1P
1^
10
#1084000
1>
b1101 8
11
#1088000
00
#1089000
1!
15
#1091000
b1010100 9
#1092000
0!
05
#1098000
b111000010001 %
b111000010001 J
0>
1?
1G
1L
1T
10
#1101000
b1110 8
#1102000
1[
1!
15
#1104000
b1010101 9
#1105000
0!
05
00
#1115000
0#
1$
0E
1F
b111010111110 %
b111010111110 J
1>
0?
1Q
1b
0L
1!
15
10
#1117000
1B
b100001011111 6
b100001011111 A
b100001011111 O
b100001011111 ]
17
b1010110 9
#1118000
0>
0!
05
01
#1122000
00
#1128000
1#
0B
1E
b100001011111 %
b100001011111 J
1M
1i
0U
b100001011111 I
b100001011111 S
1!
15
#1130000
b0 6
b0 A
b0 O
b0 ]
07
b1010111 9
#1131000
0!
05
#1132000
0X
10
#1139000
00
#1141000
0#
0D
1_
1!
15
#1143000
b1011000 9
#1144000
0!
05
#1149000
0$
0G
0P
10
#1152000
1>
b1111 8
11
#1154000
1!
15
#1156000
b1011001 9
00
#1157000
0!
05
#1166000
1$
b111000010001 %
b111000010001 J
0>
1?
1G
1L
0T
10
#1167000
0[
1!
15
#1169000
1C
0?
b100111000011 6
b100111000011 A
b100111000011 O
b100111000011 ]
17
b1011010 9
01
#1170000
0!
05
#1173000
00
#1180000
0C
b100111000011 %
b100111000011 J
1B
1D
0E
0M
0c
b100111000011 H
b100111000011 a
0Q
1!
15
#1182000
b101101100010 6
b101101100010 A
b101101100010 O
b101101100010 ]
b1011011 9
#1183000
0f
0!
05
10
#1190000
00
#1193000
1#
0B
1E
1U
b101101100010 I
b101101100010 S
1M
1!
15
#1195000
b0 6
b0 A
b0 O
b0 ]
07
b1011100 9
#1196000
0!
05
#1200000
0$
0F
0^
1X
10
#1203000
1?
b10000 8
11
#1206000
1!
15
#1207000
00
#1208000
b1011101 9
#1209000
0!
05
#1217000
0$
0G
1F
b101101100010 %
b101101100010 J
1>
0?
1P
0b
0L
10
#1219000
0i
1!
15
#1220000
b10001 8
#1221000
b1011110 9
#1222000
0!
05
#1224000
00
#1232000
0#
0D
0_
1!
15
#1234000
1$
b100111000011 %
b100111000011 J
0>
1?
1G
1L
1T
1C
b100011011001 6
b100011011001 A
b100011011001 O
b100011011001 ]
17
b1011111 9
10
#1235000
0!
05
#1237000
0?
01
#1241000
00
#1245000
b100011011001 %
b100011011001 J
1#
0C
1D
1[
1c
b100011011001 H
b100011011001 a
0M
1!
15
#1247000
b0 6
b0 A
b0 O
b0 ]
07
b1100000 9
#1248000
0!
05
#1251000
1f
10
#1258000
0#
0E
1Q
00
1!
15
#1260000
1B
b111110011111 6
b111110011111 A
b111110011111 O
b111110011111 ]
17
b1100001 9
#1261000
0!
05
#1268000
0$
0F
1^
10
#1271000
1#
0B
1E
0U
b111110011111 I
b111110011111 S
1M
1?
b10010 8
11
1!
15
#1273000
b0 6
b0 A
b0 O
b0 ]
07
b1100010 9
#1274000
0!
05
#1275000
00
#1284000
1!
15
#1285000
1$
1F
b111110011111 %
b111110011111 J
1>
0?
0X
1b
0L
10
#1286000
b1100011 9
#1287000
0!
05
#1288000
0>
01
#1292000
00
#1297000
1i
1!
15
#1299000
b1100100 9
#1300000
0!
05
#1302000
0$
0G
0P
10
#1305000
1>
b10011 8
11
#1309000
00
#1310000
0#
0D
1_
1!
15
#1312000
1C
b11110111111 6
b11110111111 A
b11110111111 O
b11110111111 ]
17
b1100101 9
#1313000
0!
05
#1319000
1$
1G
b100011011001 %
b100011011001 J
0>
1?
0T
1L
10
#1322000
0?
01
#1323000
b11110111111 %
b11110111111 J
1#
0C
1D
0[
0c
b11110111111 H
b11110111111 a
0M
1!
15
#1325000
b0 6
b0 A
b0 O
b0 ]
07
b1100110 9
#1326000
0!
05
00
#1336000
0#
0E
0Q
0f
1!
15
10
#1338000
b1100111 9
#1339000
0!
05
#1343000
00
#1349000
1!
15
#1351000
1B
b110110110110 6
b110110110110 A
b110110110110 O
b110110110110 ]
17
b1101000 9
#1352000
0!
05
#1353000
0$
0F
0^
10
#1356000
1?
b10100 8
11
#1360000
00
#1362000
1#
0B
1E
1M
1U
b110110110110 I
b110110110110 S
1!
15
#1364000
b0 6
b0 A
b0 O
b0 ]
07
b1101001 9
#1365000
0!
05
#1370000
1$
b110110110110 %
b110110110110 J
1>
0?
1F
0L
0b
1X
10
#1373000
0>
01
#1375000
0i
1!
15
#1377000
b1101010 9
00
#1378000
0!
05
#1387000
0$
0G
1P
10
#1388000
0#
0D
0_
1!
15
#1390000
1C
1>
b10000011000 6
b10000011000 A
b10000011000 O
b10000011000 ]
17
b1101011 9
b10101 8
11
#1391000
0!
05
#1394000
00
#1401000
1#
0C
1D
1c
b10000011000 H
b10000011000 a
0M
1!
15
#1403000
b0 6
b0 A
b0 O
b0 ]
07
b1101100 9
#1404000
1$
b10000011000 %
b10000011000 J
0>
1?
1G
1L
1f
1T
0!
05
10
#1407000
0?
01
#1411000
00
#1414000
1[
1!
15
#1416000
b1101101 9
#1417000
0!
05
#1421000
0$
0F
1^
10
#1424000
1?
b10110 8
11
#1427000
0#
0E
1Q
1!
15
#1428000
00
#1429000
b1101110 9
#1430000
0!
05
#1438000
1$
b110110110110 %
b110110110110 J
1>
0?
1F
0L
1b
10
#1440000
1i
1!
15
#1441000
0>
01
#1442000
1B
b110100101110 6
b110100101110 A
b110100101110 O
b110100101110 ]
17
b1101111 9
#1443000
0!
05
#1445000
00
#1453000
0#
0B
1C
1E
b110100101110 %
b110100101110 J
0D
0U
b110100101110 I
b110100101110 S
1_
1M
1!
15
#1455000
0X
b110111001010 6
b110111001010 A
b110111001010 O
b110111001010 ]
b1110000 9
10
#1456000
0!
05
#1462000
00
#1466000
1#
0C
1D
0M
0c
b110111001010 H
b110111001010 a
1!
15
#1468000
b0 6
b0 A
b0 O
b0 ]
07
b1110001 9
#1469000
0!
05
#1472000
0$
0G
0f
0P
10
#1475000
1>
b10111 8
11
#1479000
00
1!
15
#1481000
b1110010 9
#1482000
0!
05
#1489000
0$
1G
0F
b110111001010 %
b110111001010 J
0>
1?
0T
0^
1L
10
#1492000
0[
b11000 8
1!
15
#1494000
b1110011 9
#1495000
0!
05
#1496000
00
#1505000
0#
0E
0Q
1!
15
#1506000
1$
b110100101110 %
b110100101110 J
1>
0?
1F
0L
0b
10
#1507000
b1110100 9
#1508000
0!
05
#1509000
0>
01
#1513000
00
#1518000
0i
1!
15
#1520000
b1110101 9
#1521000
0!
05
#1523000
10
#1530000
00
#1531000
0D
0_
1!
15
#1533000
1B
b10101111010 6
b10101111010 A
b10101111010 O
b10101111010 ]
17
b1110110 9
#1534000
0!
05
#1540000
10
#1544000
1C
0B
1E
b10101111010 %
b10101111010 J
1M
1U
b10101111010 I
b10101111010 S
1!
15
#1546000
b1000111100111 6
b1000111100111 A
b1000111100111 O
b1000111100111 ]
b1110111 9
#1547000
0!
05
00
#1557000
1#
0C
1D
1c
b1000111100111 H
b1000111100111 a
0M
1X
1!
15
10
#1559000
b0 6
b0 A
b0 O
b0 ]
07
b1111000 9
#1560000
0!
05
#1564000
00
#1570000
1!
15
#1572000
b1111001 9
#1573000
0!
05
#1574000
0$
0G
1f
1P
10
#1577000
1>
b11001 8
11
#1581000
00
#1583000
1!
15
#1585000
b1111010 9
#1586000
0!
05
#1591000
0$
1G
0F
b1000111100111 %
b1000111100111 J
0>
1?
1T
1^
1L
10
#1594000
b11010 8
#1596000
1[
1!
15
#1598000
b1111011 9
00
#1599000
0!
05
#1608000
1$
b10101111010 %
b10101111010 J
1>
0?
1F
0L
1b
10
#1609000
0#
0E
1Q
1i
1!
15
#1611000
0>
b1111100 9
01
#1612000
0!
05
#1615000
00
#1622000
0D
1_
1!
15
#1624000
b1111101 9
#1625000
0!
05
10
#1632000
00
#1635000
1!
15
#1637000
b1111110 9
#1638000
0!
05
#1642000
10
#1648000
1!
15
#1649000
00
#1650000
b1111111 9
#1651000
0!
05
#1659000
10
#1661000
1!
15
#1663000
b10000000 9
#1664000
0!
05
#1666000
00
#1674000
1!
15
#1676000
b10000001 9
10
#1677000
0!
05
#1683000
00
#1687000
1!
15
#1689000
1B
b1001000010001 6
b1001000010001 A
b1001000010001 O
b1001000010001 ]
17
b10000010 9
#1690000
0!
05
#1693000
10
#1700000
1C
0B
1E
b1001000010001 %
b1001000010001 J
1M
0U
b1001000010001 I
b1001000010001 S
00
1!
15
#1702000
b110000011101 6
b110000011101 A
b110000011101 O
b110000011101 ]
b10000011 9
