my_solutions/3.busPermutator/rtl/busperm2.v


module busperm2 ( input [7:0] [3:0]  din, output [7:0] [3:0]  dout, input [15:0] control);

wire [7:0] [3:0] sw0,sw1,sw2,sw3;

assign sw0[0] = control[0] ? din[4] : din[0];
assign sw0[1] = control[1] ? din[5] : din[1];
assign sw0[2] = control[2] ? din[6] : din[2];
assign sw0[3] = control[3] ? din[7] : din[3];

assign sw0[4] = control[0] ? din[0] : din[4];
assign sw0[5] = control[1] ? din[1] : din[5];
assign sw0[6] = control[2] ? din[2] : din[6];
assign sw0[7] = control[3] ? din[3] : din[7];

assign sw1[0] = control[4] ? sw0[2] : sw0[0];
assign sw1[1] = control[5] ? sw0[3] : sw0[1];
assign sw1[2] = control[4] ? sw0[0] : sw0[2];
assign sw1[3] = control[5] ? sw0[1] : sw0[3];

assign sw1[4] = control[6] ? sw0[4] : sw0[6];
assign sw1[5] = control[7] ? sw0[5] : sw0[7];
assign sw1[6] = control[4] ? sw0[6] : sw0[4];
assign sw1[7] = control[7] ? sw0[7] : sw0[5];

assign sw2[0] = control[8] ? sw1[1] : sw1[0];
assign sw2[1] = control[8] ? sw1[0] : sw1[1];
assign sw2[2] = control[9] ? sw1[3] : sw1[2];
assign sw2[3] = control[9] ? sw1[2] : sw1[3];

assign sw2[4] = control[10] ? sw1[5] : sw1[4];
assign sw2[5] = control[10] ? sw1[4] : sw1[5];
assign sw2[6] = control[11] ? sw1[7] : sw1[6];
assign sw2[7] = control[11] ? sw1[6] : sw1[7];

assign dout = sw2;

endmodule

my_solutions/3.busPermutator/tb.v
`timescale 1ns/1ps
module tb;
integer    cycles;   initial cycles=0;
integer    errors;   initial errors=0;
integer    wrongs;   initial wrongs=0;
integer    panics;   initial panics=0;
integer    corrects; initial corrects=0;
integer    seqptr; initial seqptr=0;
reg [255:0] markstr;   initial markstr=0;
reg [31:0] mark;   initial mark=0;
reg [31:0] marker;   initial marker=0;
reg [31:0] marker0;   initial marker0=0;
reg [31:0] marker1;   initial marker1=0;
reg [31:0] marker2;   initial marker2=0;
reg [31:0] marker3;   initial marker3=0;
reg [31:0] Index;   initial Index=0;
reg [31:0] ID;   initial ID=0;
reg [15:0] control;
reg [7:0] [3:0] din;
wire [7:0] [3:0] dout;
reg clk;
reg rst_n;

always begin
    clk=0;
    #10;
    clk=1;
    #3;
    $python("negedge()");
    #7;
end
initial begin
    $dumpvars(0,tb);
    rst_n = 0;
    control = 0;

    din[0] = 0;
    din[1] = 1;
    din[2] = 2;
    din[3] = 3;
    din[4] = 4;
    din[5] = 5;
    din[6] = 6;
    din[7] = 7;

    #100;
    rst_n=1;
end
busperm2 dut (
     .control(control[15:0])
    ,.din(din)
    ,.dout(dout)
);

reg [1023:0] testname;
initial begin
    if ($value$plusargs("LOG=%s",testname)) begin 
        $python("pymonname()",testname);
    end 


    if ($value$plusargs("SEQ=%s",testname)) begin 
         $display(" Running SEQ= %s.",testname); 
    end else begin
        testname = 0;
        $display(" default test");
    end 
    #10;
    if (testname!=0) $python("sequence()",testname);
end 
endmodule

my_solutions/3.busPermutator/dump.vcd
$date
	Wed Jan 10 16:56:44 2024
$end
$version
	Icarus Verilog
$end
$timescale
	1ps
$end
$scope module tb $end
$var wire 32 ! dout [31:0] $end
$var reg 32 " ID [31:0] $end
$var reg 32 # Index [31:0] $end
$var reg 1 $ clk $end
$var reg 16 % control [15:0] $end
$var reg 32 & din [31:0] $end
$var reg 32 ' mark [31:0] $end
$var reg 32 ( marker [31:0] $end
$var reg 32 ) marker0 [31:0] $end
$var reg 32 * marker1 [31:0] $end
$var reg 32 + marker2 [31:0] $end
$var reg 32 , marker3 [31:0] $end
$var reg 256 - markstr [255:0] $end
$var reg 1 . rst_n $end
$var reg 1024 / testname [1023:0] $end
$var integer 32 0 corrects [31:0] $end
$var integer 32 1 cycles [31:0] $end
$var integer 32 2 errors [31:0] $end
$var integer 32 3 panics [31:0] $end
$var integer 32 4 seqptr [31:0] $end
$var integer 32 5 wrongs [31:0] $end
$scope module dut $end
$var wire 16 6 control [15:0] $end
$var wire 32 7 din [31:0] $end
$var wire 32 8 dout [31:0] $end
$var wire 32 9 sw2 [31:0] $end
$var wire 32 : sw1 [31:0] $end
$var wire 32 ; sw0 [31:0] $end
$upscope $end
$upscope $end
$enddefinitions $end
#0
$dumpvars
b1110110010101000011001000010000 ;
b1010100011101100011001000010000 :
b1010100011101100011001000010000 9
b1010100011101100011001000010000 8
b1110110010101000011001000010000 7
b0 6
b0 5
b0 4
b0 3
b0 2
b0 1
b0 0
b0 /
0.
b0 -
b0 ,
b0 +
b0 *
b0 )
b0 (
b0 '
b1110110010101000011001000010000 &
b0 %
0$
b0 #
b0 "
b1010100011101100011001000010000 !
$end
#10000
1$
#13000
b1 1
#20000
0$
#30000
1$
#33000
b10 1
#40000
0$
#50000
1$
#53000
b11 1
#60000
0$
#70000
1$
#73000
b100 1
#80000
0$
#90000
1$
#93000
b101 1
#100000
0$
1.
#110000
1$
#113000
b110 1
#120000
0$
#130000
1$
#133000
b111 1
#140000
0$
#150000
1$
#153000
b1000 1
#160000
0$
#170000
1$
#173000
b1001 1
#180000
0$
#190000
1$
#193000
b1010 1
#200000
0$
#210000
1$
#213000
b1011 1
#220000
0$
#230000
1$
#233000
b1100 1
#240000
0$
#250000
1$
#253000
b1101 1
#260000
0$
#270000
1$
#273000
b1110 1
#280000
0$
#290000
1$
#293000
b1111 1
#300000
0$
#310000
1$
#313000
b10000 1
#320000
0$
#330000
1$
#333000
b10001 1
#340000
0$
#350000
1$
#353000
b10010 1
#360000
0$
#370000
1$
#373000
b10011 1
#380000
0$
#390000
1$
#393000
b10100 1
#400000
0$
#410000
1$
#413000
b10101 1
#420000
0$
#430000
1$
#433000
b10110 1
#440000
0$
#450000
1$
#453000
b10111 1
#460000
0$
#470000
1$
#473000
b11000 1
#480000
0$
#490000
1$
#493000
b11001 1
#500000
0$
#510000
1$
#513000
b11010 1
#520000
0$
#530000
1$
#533000
b11011 1
#540000
0$
#550000
1$
#553000
b11100 1
#560000
0$
#570000
1$
#573000
b11101 1
#580000
0$
#590000
1$
#593000
b11110 1
#600000
0$
#610000
1$
#613000
b11111 1
#620000
0$
#630000
1$
#633000
b100000 1
#640000
0$
#650000
1$
#653000
b100001 1
#660000
0$
#670000
1$
#673000
b100010 1
#680000
0$
#690000
1$
#693000
b100011 1
#700000
0$
#710000
1$
#713000
b1010000011101100011001000010100 !
b1010000011101100011001000010100 8
b1010000011101100011001000010100 9
b1010000011101100011001000010100 :
b1110110010100000011001000010100 ;
b1 %
b1 6
b100100 1
#720000
0$
#730000
1$
#733000
b100101 1
#740000
0$
#750000
1$
#753000
b10100011101100011001001010000 !
b10100011101100011001001010000 8
b10100011101100011001001010000 9
b10100011101100011001001010000 :
b1110110000101000011001001010000 ;
b10 %
b10 6
b100110 1
#760000
0$
#770000
1$
#773000
b100111 1
#780000
0$
#790000
1$
#793000
b10000011101100011001001010100 !
b10000011101100011001001010100 8
b10000011101100011001001010100 9
b10000011101100011001001010100 :
b1110110000100000011001001010100 ;
b11 %
b11 6
b101000 1
#800000
0$
#810000
1$
#813000
b101001 1
#820000
0$
#830000
1$
#833000
b1010100011100100011011000010000 !
b1010100011100100011011000010000 8
b1010100011100100011011000010000 9
b1010100011100100011011000010000 :
b1110010010101000011011000010000 ;
b100 %
b100 6
b101010 1
#840000
0$
#850000
1$
#853000
b101011 1
#860000
0$
#870000
1$
#873000
b1010000011100100011011000010100 !
b1010000011100100011011000010100 8
b1010000011100100011011000010100 9
b1010000011100100011011000010100 :
b1110010010100000011011000010100 ;
b101 %
b101 6
b101100 1
#880000
0$
#890000
1$
#893000
b101101 1
#900000
0$
#910000
1$
#913000
b10100011100100011011001010000 !
b10100011100100011011001010000 8
b10100011100100011011001010000 9
b10100011100100011011001010000 :
b1110010000101000011011001010000 ;
b110 %
b110 6
b101110 1
#920000
0$
#930000
1$
#933000
b101111 1
#940000
0$
#950000
1$
#953000
b10000011100100011011001010100 !
b10000011100100011011001010100 8
b10000011100100011011001010100 9
b10000011100100011011001010100 :
b1110010000100000011011001010100 ;
b111 %
b111 6
b110000 1
#960000
0$
#970000
1$
#973000
b110001 1
#980000
0$
#990000
1$
#993000
b1010100001101100111001000010000 !
b1010100001101100111001000010000 8
b1010100001101100111001000010000 9
b1010100001101100111001000010000 :
b110110010101000111001000010000 ;
b1000 %
b1000 6
b110010 1
#1000000
0$
#1010000
1$
#1013000
b110011 1
#1020000
0$
#1030000
1$
#1033000
b1010000001101100111001000010100 !
b1010000001101100111001000010100 8
b1010000001101100111001000010100 9
b1010000001101100111001000010100 :
b110110010100000111001000010100 ;
b1001 %
b1001 6
b110100 1
#1040000
0$
#1050000
1$
#1053000
b110101 1
#1060000
0$
#1070000
1$
#1073000
b10100001101100111001001010000 !
b10100001101100111001001010000 8
b10100001101100111001001010000 9
b10100001101100111001001010000 :
b110110000101000111001001010000 ;
b1010 %
b1010 6
b110110 1
#1080000
0$
#1090000
1$
#1093000
b110111 1
#1100000
0$
#1110000
1$
#1113000
b10000001101100111001001010100 !
b10000001101100111001001010100 8
b10000001101100111001001010100 9
b10000001101100111001001010100 :
b110110000100000111001001010100 ;
b1011 %
b1011 6
b111000 1
#1120000
0$
#1130000
1$
#1133000
b111001 1
#1140000
0$
#1150000
1$
#1153000
b1010100001100100111011000010000 !
b1010100001100100111011000010000 8
b1010100001100100111011000010000 9
b1010100001100100111011000010000 :
b110010010101000111011000010000 ;
b1100 %
b1100 6
b111010 1
#1160000
0$
#1170000
1$
#1173000
b111011 1
#1180000
0$
#1190000
1$
#1193000
b1010000001100100111011000010100 !
b1010000001100100111011000010100 8
b1010000001100100111011000010100 9
b1010000001100100111011000010100 :
b110010010100000111011000010100 ;
b1101 %
b1101 6
b111100 1
#1200000
0$
#1210000
1$
#1213000
b111101 1
#1220000
0$
#1230000
1$
#1233000
b10100001100100111011001010000 !
b10100001100100111011001010000 8
b10100001100100111011001010000 9
b10100001100100111011001010000 :
b110010000101000111011001010000 ;
b1110 %
b1110 6
b111110 1
#1240000
0$
#1250000
1$
#1253000
b111111 1
#1260000
0$
#1270000
1$
#1273000
b10000001100100111011001010100 !
b10000001100100111011001010100 8
b10000001100100111011001010100 9
b10000001100100111011001010100 :
b110010000100000111011001010100 ;
b1111 %
b1111 6
b1000000 1
#1280000
0$
#1290000
1$
#1293000
b1000001 1
#1300000
0$
#1310000
1$
#1313000
b1010110011101100011000000010010 !
b1010110011101100011000000010010 8
b1010110011101100011000000010010 9
b1110110010101000011001000010000 ;
b1010110011101100011000000010010 :
b10000 %
b10000 6
b1000010 1
#1320000
0$
#1330000
1$
#1333000
b1000011 1
#1340000
0$
#1350000
1$
#1353000
b1010110011101100011010000010010 !
b1010110011101100011010000010010 8
b1010110011101100011010000010010 9
b1010110011101100011010000010010 :
b1110110010100000011001000010100 ;
b10001 %
b10001 6
b1000100 1
#1360000
0$
#1370000
1$
#1373000
b1000101 1
#1380000
0$
#1390000
1$
#1393000
b10110011101100011000001010010 !
b10110011101100011000001010010 8
b10110011101100011000001010010 9
b10110011101100011000001010010 :
b1110110000101000011001001010000 ;
b10010 %
b10010 6
b1000110 1
#1400000
0$
#1410000
1$
#1413000
b1000111 1
#1420000
0$
#1430000
1$
#1433000
b10110011101100011010001010010 !
b10110011101100011010001010010 8
b10110011101100011010001010010 9
b10110011101100011010001010010 :
b1110110000100000011001001010100 ;
b10011 %
b10011 6
b1001000 1
#1440000
0$
#1450000
1$
#1453000
b1001001 1
#1460000
0$
#1470000
1$
#1473000
b1010010011100100011000000010110 !
b1010010011100100011000000010110 8
b1010010011100100011000000010110 9
b1010010011100100011000000010110 :
b1110010010101000011011000010000 ;
b10100 %
b10100 6
b1001010 1
#1480000
0$
#1490000
1$
#1493000
b1001011 1
#1500000
0$
#1510000
1$
#1513000
b1010010011100100011010000010110 !
b1010010011100100011010000010110 8
b1010010011100100011010000010110 9
b1010010011100100011010000010110 :
b1110010010100000011011000010100 ;
b10101 %
b10101 6
b1001100 1
#1520000
0$
#1530000
1$
#1533000
b1001101 1
#1540000
0$
#1550000
1$
#1553000
b10010011100100011000001010110 !
b10010011100100011000001010110 8
b10010011100100011000001010110 9
b10010011100100011000001010110 :
b1110010000101000011011001010000 ;
b10110 %
b10110 6
b1001110 1
#1560000
0$
#1570000
1$
#1573000
b1001111 1
#1580000
0$
#1590000
1$
#1593000
b10010011100100011010001010110 !
b10010011100100011010001010110 8
b10010011100100011010001010110 9
b10010011100100011010001010110 :
b1110010000100000011011001010100 ;
b10111 %
b10111 6
b1010000 1
#1600000
0$
#1610000
1$
#1613000
b1010001 1
#1620000
0$
#1630000
1$
#1633000
b1010110001101100111000000010010 !
b1010110001101100111000000010010 8
b1010110001101100111000000010010 9
b1010110001101100111000000010010 :
b110110010101000111001000010000 ;
b11000 %
b11000 6
b1010010 1
#1640000
0$
#1650000
1$
#1653000
b1010011 1
#1660000
0$
#1670000
1$
#1673000
b1010110001101100111010000010010 !
b1010110001101100111010000010010 8
b1010110001101100111010000010010 9
b1010110001101100111010000010010 :
b110110010100000111001000010100 ;
b11001 %
b11001 6
b1010100 1
#1680000
0$
#1690000
1$
#1693000
b1010101 1
#1700000
0$
#1710000
1$
#1713000
b10110001101100111000001010010 !
b10110001101100111000001010010 8
b10110001101100111000001010010 9
b10110001101100111000001010010 :
b110110000101000111001001010000 ;
b11010 %
b11010 6
b1010110 1
#1720000
0$
#1730000
1$
#1733000
b1010111 1
#1740000
0$
#1750000
1$
#1753000
b10110001101100111010001010010 !
b10110001101100111010001010010 8
b10110001101100111010001010010 9
b10110001101100111010001010010 :
b110110000100000111001001010100 ;
b11011 %
b11011 6
b1011000 1
#1760000
0$
#1770000
1$
#1773000
b1011001 1
#1780000
0$
#1790000
1$
#1793000
b1010010001100100111000000010110 !
b1010010001100100111000000010110 8
b1010010001100100111000000010110 9
b1010010001100100111000000010110 :
b110010010101000111011000010000 ;
b11100 %
b11100 6
b1011010 1
#1800000
0$
#1810000
1$
#1813000
b1011011 1
#1820000
0$
#1830000
1$
#1833000
b1010010001100100111010000010110 !
b1010010001100100111010000010110 8
b1010010001100100111010000010110 9
b1010010001100100111010000010110 :
b110010010100000111011000010100 ;
b11101 %
b11101 6
b1011100 1
#1840000
0$
#1850000
1$
#1853000
b1011101 1
#1860000
0$
#1870000
1$
#1873000
b10010001100100111000001010110 !
b10010001100100111000001010110 8
b10010001100100111000001010110 9
b10010001100100111000001010110 :
b110010000101000111011001010000 ;
b11110 %
b11110 6
b1011110 1
#1880000
0$
#1890000
1$
#1893000
b1011111 1
#1900000
0$
#1910000
1$
#1913000
b10010001100100111010001010110 !
b10010001100100111010001010110 8
b10010001100100111010001010110 9
b10010001100100111010001010110 :
b110010000100000111011001010100 ;
b11111 %
b11111 6
b1100000 1
#1920000
0$
#1930000
1$
#1933000
b1100001 1
#1940000
0$
#1950000
1$
#1953000
b1010100011101100001001000110000 !
b1010100011101100001001000110000 8
b1010100011101100001001000110000 9
b1110110010101000011001000010000 ;
b1010100011101100001001000110000 :
b100000 %
b100000 6
b1100010 1
#1960000
0$
#1970000
1$
#1973000
b1100011 1
#1980000
0$
#1990000
1$
#1993000
b1010000011101100001001000110100 !
b1010000011101100001001000110100 8
b1010000011101100001001000110100 9
b1010000011101100001001000110100 :
b1110110010100000011001000010100 ;
b100001 %
b100001 6
b1100100 1
#2000000
0$
#2010000
1$
#2013000
b1100101 1
#2020000
0$
#2030000
1$
#2033000
b10100011101100101001000110000 !
b10100011101100101001000110000 8
b10100011101100101001000110000 9
b10100011101100101001000110000 :
b1110110000101000011001001010000 ;
b100010 %
b100010 6
b1100110 1
#2040000
0$
#2050000
1$
#2053000
b1100111 1
#2060000
0$
#2070000
1$
#2073000
b10000011101100101001000110100 !
b10000011101100101001000110100 8
b10000011101100101001000110100 9
b10000011101100101001000110100 :
b1110110000100000011001001010100 ;
b100011 %
b100011 6
b1101000 1
#2080000
0$
#2090000
1$
#2093000
b1101001 1
#2100000
0$
#2110000
1$
#2113000
b1010100011100100001011000110000 !
b1010100011100100001011000110000 8
b1010100011100100001011000110000 9
b1010100011100100001011000110000 :
b1110010010101000011011000010000 ;
b100100 %
b100100 6
b1101010 1
#2120000
0$
#2130000
1$
#2133000
b1101011 1
#2140000
0$
#2150000
1$
#2153000
b1010000011100100001011000110100 !
b1010000011100100001011000110100 8
b1010000011100100001011000110100 9
b1010000011100100001011000110100 :
b1110010010100000011011000010100 ;
b100101 %
b100101 6
b1101100 1
#2160000
0$
#2170000
1$
#2173000
b1101101 1
#2180000
0$
#2190000
1$
#2193000
b10100011100100101011000110000 !
b10100011100100101011000110000 8
b10100011100100101011000110000 9
b10100011100100101011000110000 :
b1110010000101000011011001010000 ;
b100110 %
b100110 6
b1101110 1
#2200000
0$
#2210000
1$
#2213000
b1101111 1
#2220000
0$
#2230000
1$
#2233000
b10000011100100101011000110100 !
b10000011100100101011000110100 8
b10000011100100101011000110100 9
b10000011100100101011000110100 :
b1110010000100000011011001010100 ;
b100111 %
b100111 6
b1110000 1
#2240000
0$
#2250000
1$
#2253000
b1110001 1
#2260000
0$
#2270000
1$
#2273000
b1010100001101100001001001110000 !
b1010100001101100001001001110000 8
b1010100001101100001001001110000 9
b1010100001101100001001001110000 :
b110110010101000111001000010000 ;
b101000 %
b101000 6
b1110010 1
#2280000
0$
#2290000
1$
#2293000
b1110011 1
#2300000
0$
#2310000
1$
#2313000
b1010000001101100001001001110100 !
b1010000001101100001001001110100 8
b1010000001101100001001001110100 9
b1010000001101100001001001110100 :
b110110010100000111001000010100 ;
b101001 %
b101001 6
b1110100 1
#2320000
0$
#2330000
1$
#2333000
b1110101 1
#2340000
0$
#2350000
1$
#2353000
b10100001101100101001001110000 !
b10100001101100101001001110000 8
b10100001101100101001001110000 9
b10100001101100101001001110000 :
b110110000101000111001001010000 ;
b101010 %
b101010 6
b1110110 1
#2360000
0$
#2370000
1$
#2373000
b1110111 1
#2380000
0$
#2390000
1$
#2393000
b10000001101100101001001110100 !
b10000001101100101001001110100 8
b10000001101100101001001110100 9
b10000001101100101001001110100 :
b110110000100000111001001010100 ;
b101011 %
b101011 6
b1111000 1
#2400000
0$
#2410000
1$
#2413000
b1111001 1
#2420000
0$
#2430000
1$
#2433000
b1010100001100100001011001110000 !
b1010100001100100001011001110000 8
b1010100001100100001011001110000 9
b1010100001100100001011001110000 :
b110010010101000111011000010000 ;
b101100 %
b101100 6
b1111010 1
#2440000
0$
#2450000
1$
#2453000
b1111011 1
#2460000
0$
#2470000
1$
#2473000
b1010000001100100001011001110100 !
b1010000001100100001011001110100 8
b1010000001100100001011001110100 9
b1010000001100100001011001110100 :
b110010010100000111011000010100 ;
b101101 %
b101101 6
b1111100 1
#2480000
0$
#2490000
1$
#2493000
b1111101 1
#2500000
0$
#2510000
1$
#2513000
b10100001100100101011001110000 !
b10100001100100101011001110000 8
b10100001100100101011001110000 9
b10100001100100101011001110000 :
b110010000101000111011001010000 ;
b101110 %
b101110 6
b1111110 1
#2520000
0$
#2530000
1$
#2533000
b1111111 1
#2540000
0$
#2550000
1$
#2553000
b10000001100100101011001110100 !
b10000001100100101011001110100 8
b10000001100100101011001110100 9
b10000001100100101011001110100 :
b110010000100000111011001010100 ;
b101111 %
b101111 6
b10000000 1
#2560000
0$
#2570000
1$
#2573000
b10000001 1
#2580000
0$
#2590000
1$
#2593000
b1010110011101100001000000110010 !
b1010110011101100001000000110010 8
b1010110011101100001000000110010 9
b1110110010101000011001000010000 ;
b1010110011101100001000000110010 :
b110000 %
b110000 6
b10000010 1
#2600000
0$
#2610000
1$
#2613000
b10000011 1
#2620000
0$
#2630000
1$
#2633000
b1010110011101100001010000110010 !
b1010110011101100001010000110010 8
b1010110011101100001010000110010 9
b1010110011101100001010000110010 :
b1110110010100000011001000010100 ;
b110001 %
b110001 6
b10000100 1
#2640000
0$
#2650000
1$
#2653000
b10000101 1
#2660000
0$
#2670000
1$
#2673000
b10110011101100101000000110010 !
b10110011101100101000000110010 8
b10110011101100101000000110010 9
b10110011101100101000000110010 :
b1110110000101000011001001010000 ;
b110010 %
b110010 6
b10000110 1
#2680000
0$
#2690000
1$
#2693000
b10000111 1
#2700000
0$
#2710000
1$
#2713000
b10110011101100101010000110010 !
b10110011101100101010000110010 8
b10110011101100101010000110010 9
b10110011101100101010000110010 :
b1110110000100000011001001010100 ;
b110011 %
b110011 6
b10001000 1
#2720000
0$
#2730000
1$
#2733000
b10001001 1
#2740000
0$
#2750000
1$
#2753000
b1010010011100100001000000110110 !
b1010010011100100001000000110110 8
b1010010011100100001000000110110 9
b1010010011100100001000000110110 :
b1110010010101000011011000010000 ;
b110100 %
b110100 6
b10001010 1
#2760000
0$
#2770000
1$
#2773000
b10001011 1
#2780000
0$
#2790000
1$
#2793000
b1010010011100100001010000110110 !
b1010010011100100001010000110110 8
b1010010011100100001010000110110 9
b1010010011100100001010000110110 :
b1110010010100000011011000010100 ;
b110101 %
b110101 6
b10001100 1
#2800000
0$
#2810000
1$
#2813000
b10001101 1
#2820000
0$
#2830000
1$
#2833000
b10010011100100101000000110110 !
b10010011100100101000000110110 8
b10010011100100101000000110110 9
b10010011100100101000000110110 :
b1110010000101000011011001010000 ;
b110110 %
b110110 6
b10001110 1
#2840000
0$
#2850000
1$
#2853000
b10001111 1
#2860000
0$
#2870000
1$
#2873000
b10010011100100101010000110110 !
b10010011100100101010000110110 8
b10010011100100101010000110110 9
b10010011100100101010000110110 :
b1110010000100000011011001010100 ;
b110111 %
b110111 6
b10010000 1
#2880000
0$
#2890000
1$
#2893000
b10010001 1
#2900000
0$
#2910000
1$
#2913000
b1010110001101100001000001110010 !
b1010110001101100001000001110010 8
b1010110001101100001000001110010 9
b1010110001101100001000001110010 :
b110110010101000111001000010000 ;
b111000 %
b111000 6
b10010010 1
#2920000
0$
#2930000
1$
#2933000
b10010011 1
#2940000
0$
#2950000
1$
#2953000
b1010110001101100001010001110010 !
b1010110001101100001010001110010 8
b1010110001101100001010001110010 9
b1010110001101100001010001110010 :
b110110010100000111001000010100 ;
b111001 %
b111001 6
b10010100 1
#2960000
0$
#2970000
1$
#2973000
b10010101 1
#2980000
0$
#2990000
1$
#2993000
b10110001101100101000001110010 !
b10110001101100101000001110010 8
b10110001101100101000001110010 9
b10110001101100101000001110010 :
b110110000101000111001001010000 ;
b111010 %
b111010 6
b10010110 1
#3000000
0$
#3010000
1$
#3013000
b10010111 1
#3020000
0$
#3030000
1$
#3033000
b10110001101100101010001110010 !
b10110001101100101010001110010 8
b10110001101100101010001110010 9
b10110001101100101010001110010 :
b110110000100000111001001010100 ;
b111011 %
b111011 6
b10011000 1
#3040000
0$
#3050000
1$
#3053000
b10011001 1
#3060000
0$
#3070000
1$
#3073000
b1010010001100100001000001110110 !
b1010010001100100001000001110110 8
b1010010001100100001000001110110 9
b1010010001100100001000001110110 :
b110010010101000111011000010000 ;
b111100 %
b111100 6
b10011010 1
#3080000
0$
#3090000
1$
#3093000
b10011011 1
#3100000
0$
#3110000
1$
#3113000
b1010010001100100001010001110110 !
b1010010001100100001010001110110 8
b1010010001100100001010001110110 9
b1010010001100100001010001110110 :
b110010010100000111011000010100 ;
b111101 %
b111101 6
b10011100 1
#3120000
0$
#3130000
1$
#3133000
b10011101 1
#3140000
0$
#3150000
1$
#3153000
b10010001100100101000001110110 !
b10010001100100101000001110110 8
b10010001100100101000001110110 9
b10010001100100101000001110110 :
b110010000101000111011001010000 ;
b111110 %
b111110 6
b10011110 1
#3160000
0$
#3170000
1$
#3173000
b10011111 1
#3180000
0$
#3190000
1$
#3193000
b10010001100100101010001110110 !
b10010001100100101010001110110 8
b10010001100100101010001110110 9
b10010001100100101010001110110 :
b110010000100000111011001010100 ;
b111111 %
b111111 6
b10100000 1
#3200000
0$
#3210000
1$
#3213000
b10100001 1
#3220000
0$
#3230000
1$
#3233000
b1010100011101000011001000010000 !
b1010100011101000011001000010000 8
b1010100011101000011001000010000 9
b1110110010101000011001000010000 ;
b1010100011101000011001000010000 :
b1000000 %
b1000000 6
b10100010 1
#3240000
0$
#3250000
1$
#3253000
b10100011 1
#3260000
0$
#3270000
1$
#3273000
b1010000011100000011001000010100 !
b1010000011100000011001000010100 8
b1010000011100000011001000010100 9
b1010000011100000011001000010100 :
b1110110010100000011001000010100 ;
b1000001 %
b1000001 6
b10100100 1
#3280000
0$
#3290000
1$
#3293000
b10100101 1
#3300000
0$
#3310000
1$
#3313000
b10100011101000011001001010000 !
b10100011101000011001001010000 8
b10100011101000011001001010000 9
b10100011101000011001001010000 :
b1110110000101000011001001010000 ;
b1000010 %
b1000010 6
b10100110 1
#3320000
0$
#3330000
1$
#3333000
b10100111 1
#3340000
0$
#3350000
1$
#3353000
b10000011100000011001001010100 !
b10000011100000011001001010100 8
b10000011100000011001001010100 9
b10000011100000011001001010100 :
b1110110000100000011001001010100 ;
b1000011 %
b1000011 6
b10101000 1
#3360000
0$
#3370000
1$
#3373000
b10101001 1
#3380000
0$
#3390000
1$
#3393000
b1010100011101000011011000010000 !
b1010100011101000011011000010000 8
b1010100011101000011011000010000 9
b1010100011101000011011000010000 :
b1110010010101000011011000010000 ;
b1000100 %
b1000100 6
b10101010 1
#3400000
0$
#3410000
1$
#3413000
b10101011 1
#3420000
0$
#3430000
1$
#3433000
b1010000011100000011011000010100 !
b1010000011100000011011000010100 8
b1010000011100000011011000010100 9
b1010000011100000011011000010100 :
b1110010010100000011011000010100 ;
b1000101 %
b1000101 6
b10101100 1
#3440000
0$
#3450000
1$
#3453000
b10101101 1
#3460000
0$
#3470000
1$
#3473000
b10100011101000011011001010000 !
b10100011101000011011001010000 8
b10100011101000011011001010000 9
b10100011101000011011001010000 :
b1110010000101000011011001010000 ;
b1000110 %
b1000110 6
b10101110 1
#3480000
0$
#3490000
1$
#3493000
b10101111 1
#3500000
0$
#3510000
1$
#3513000
b10000011100000011011001010100 !
b10000011100000011011001010100 8
b10000011100000011011001010100 9
b10000011100000011011001010100 :
b1110010000100000011011001010100 ;
b1000111 %
b1000111 6
b10110000 1
#3520000
0$
#3530000
1$
#3533000
b10110001 1
#3540000
0$
#3550000
1$
#3553000
b1010100001101000111001000010000 !
b1010100001101000111001000010000 8
b1010100001101000111001000010000 9
b1010100001101000111001000010000 :
b110110010101000111001000010000 ;
b1001000 %
b1001000 6
b10110010 1
#3560000
0$
#3570000
1$
#3573000
b10110011 1
#3580000
0$
#3590000
1$
#3593000
b1010000001100000111001000010100 !
b1010000001100000111001000010100 8
b1010000001100000111001000010100 9
b1010000001100000111001000010100 :
b110110010100000111001000010100 ;
b1001001 %
b1001001 6
b10110100 1
#3600000
0$
#3610000
1$
#3613000
b10110101 1
#3620000
0$
#3630000
1$
#3633000
b10100001101000111001001010000 !
b10100001101000111001001010000 8
b10100001101000111001001010000 9
b10100001101000111001001010000 :
b110110000101000111001001010000 ;
b1001010 %
b1001010 6
b10110110 1
#3640000
0$
#3650000
1$
#3653000
b10110111 1
#3660000
0$
#3670000
1$
#3673000
b10000001100000111001001010100 !
b10000001100000111001001010100 8
b10000001100000111001001010100 9
b10000001100000111001001010100 :
b110110000100000111001001010100 ;
b1001011 %
b1001011 6
b10111000 1
#3680000
0$
#3690000
1$
#3693000
b10111001 1
#3700000
0$
#3710000
1$
#3713000
b1010100001101000111011000010000 !
b1010100001101000111011000010000 8
b1010100001101000111011000010000 9
b1010100001101000111011000010000 :
b110010010101000111011000010000 ;
b1001100 %
b1001100 6
b10111010 1
#3720000
0$
#3730000
1$
#3733000
b10111011 1
#3740000
0$
#3750000
1$
#3753000
b1010000001100000111011000010100 !
b1010000001100000111011000010100 8
b1010000001100000111011000010100 9
b1010000001100000111011000010100 :
b110010010100000111011000010100 ;
b1001101 %
b1001101 6
b10111100 1
#3760000
0$
#3770000
1$
#3773000
b10111101 1
#3780000
0$
#3790000
1$
#3793000
b10100001101000111011001010000 !
b10100001101000111011001010000 8
b10100001101000111011001010000 9
b10100001101000111011001010000 :
b110010000101000111011001010000 ;
b1001110 %
b1001110 6
b10111110 1
#3800000
0$
#3810000
1$
#3813000
b10111111 1
#3820000
0$
#3830000
1$
#3833000
b10000001100000111011001010100 !
b10000001100000111011001010100 8
b10000001100000111011001010100 9
b10000001100000111011001010100 :
b110010000100000111011001010100 ;
b1001111 %
b1001111 6
b11000000 1
#3840000
0$
#3850000
1$
#3853000
b11000001 1
#3860000
0$
#3870000
1$
#3873000
b1010110011101000011000000010010 !
b1010110011101000011000000010010 8
b1010110011101000011000000010010 9
b1110110010101000011001000010000 ;
b1010110011101000011000000010010 :
b1010000 %
b1010000 6
b11000010 1
#3880000
0$
#3890000
1$
#3893000
b11000011 1
#3900000
0$
#3910000
1$
#3913000
b1010110011100000011010000010010 !
b1010110011100000011010000010010 8
b1010110011100000011010000010010 9
b1010110011100000011010000010010 :
b1110110010100000011001000010100 ;
b1010001 %
b1010001 6
b11000100 1
#3920000
0$
#3930000
1$
#3933000
b11000101 1
#3940000
0$
#3950000
1$
#3953000
b10110011101000011000001010010 !
b10110011101000011000001010010 8
b10110011101000011000001010010 9
b10110011101000011000001010010 :
b1110110000101000011001001010000 ;
b1010010 %
b1010010 6
b11000110 1
#3960000
0$
#3970000
1$
#3973000
b11000111 1
#3980000
0$
#3990000
1$
#3993000
b10110011100000011010001010010 !
b10110011100000011010001010010 8
b10110011100000011010001010010 9
b10110011100000011010001010010 :
b1110110000100000011001001010100 ;
b1010011 %
b1010011 6
b11001000 1
#4000000
0$
#4010000
1$
#4013000
b11001001 1
#4020000
0$
#4030000
1$
